{
  "openapi": "3.0.1",
  "info": {
    "title": "BlogApi",
    "version": "1.0"
  },
  "paths": {
    "/api/Category/GetCategory": {
      "get": {
        "tags": [
          "Category"
        ],
        "responses": {
          "200": {
            "description": "OK"
          }
        }
      }
    },
    "/api/Category/GetById": {
      "get": {
        "tags": [
          "Category"
        ],
        "parameters": [
          {
            "name": "id",
            "in": "query",
            "schema": {
              "type": "integer",
              "format": "int32"
            }
          }
        ],
        "responses": {
          "200": {
            "description": "OK"
          }
        }
      }
    },
    "/api/Category/CreateCategory": {
      "post": {
        "tags": [
          "Category"
        ],
        "requestBody": {
          "content": {
            "application/json": {
              "schema": {
                "$ref": "#/components/schemas/CreateCategoryRequestDto"
              }
            },
            "text/json": {
              "schema": {
                "$ref": "#/components/schemas/CreateCategoryRequestDto"
              }
            },
            "application/*+json": {
              "schema": {
                "$ref": "#/components/schemas/CreateCategoryRequestDto"
              }
            }
          }
        },
        "responses": {
          "200": {
            "description": "OK"
          }
        }
      }
    },
    "/api/Category/UpdateCategory": {
      "post": {
        "tags": [
          "Category"
        ],
        "requestBody": {
          "content": {
            "application/json": {
              "schema": {
                "$ref": "#/components/schemas/UpdateCategoryRequestDto"
              }
            },
            "text/json": {
              "schema": {
                "$ref": "#/components/schemas/UpdateCategoryRequestDto"
              }
            },
            "application/*+json": {
              "schema": {
                "$ref": "#/components/schemas/UpdateCategoryRequestDto"
              }
            }
          }
        },
        "responses": {
          "200": {
            "description": "OK"
          }
        }
      }
    },
    "/api/Category/DeleteCategory": {
      "delete": {
        "tags": [
          "Category"
        ],
        "requestBody": {
          "content": {
            "application/json": {
              "schema": {
                "$ref": "#/components/schemas/DeleteCategoryRequestDto"
              }
            },
            "text/json": {
              "schema": {
                "$ref": "#/components/schemas/DeleteCategoryRequestDto"
              }
            },
            "application/*+json": {
              "schema": {
                "$ref": "#/components/schemas/DeleteCategoryRequestDto"
              }
            }
          }
        },
        "responses": {
          "200": {
            "description": "OK"
          }
        }
      }
    },
    "/api/Comment/GetComment": {
      "get": {
        "tags": [
          "Comment"
        ],
        "responses": {
          "200": {
            "description": "OK"
          }
        }
      }
    },
    "/api/Comment/GetById": {
      "get": {
        "tags": [
          "Comment"
        ],
        "parameters": [
          {
            "name": "id",
            "in": "query",
            "schema": {
              "type": "integer",
              "format": "int32"
            }
          }
        ],
        "responses": {
          "200": {
            "description": "OK"
          }
        }
      }
    },
    "/api/Comment/CreateComment": {
      "post": {
        "tags": [
          "Comment"
        ],
        "requestBody": {
          "content": {
            "application/json": {
              "schema": {
                "$ref": "#/components/schemas/CreateCommentRequestDto"
              }
            },
            "text/json": {
              "schema": {
                "$ref": "#/components/schemas/CreateCommentRequestDto"
              }
            },
            "application/*+json": {
              "schema": {
                "$ref": "#/components/schemas/CreateCommentRequestDto"
              }
            }
          }
        },
        "responses": {
          "200": {
            "description": "OK"
          }
        }
      }
    },
    "/api/Comment/UpdateComment": {
      "post": {
        "tags": [
          "Comment"
        ],
        "requestBody": {
          "content": {
            "application/json": {
              "schema": {
                "$ref": "#/components/schemas/UpdateCommentRequestDto"
              }
            },
            "text/json": {
              "schema": {
                "$ref": "#/components/schemas/UpdateCommentRequestDto"
              }
            },
            "application/*+json": {
              "schema": {
                "$ref": "#/components/schemas/UpdateCommentRequestDto"
              }
            }
          }
        },
        "responses": {
          "200": {
            "description": "OK"
          }
        }
      }
    },
    "/api/Comment/DeleteComment": {
      "delete": {
        "tags": [
          "Comment"
        ],
        "requestBody": {
          "content": {
            "application/json": {
              "schema": {
                "$ref": "#/components/schemas/DeleteCommentRequestDto"
              }
            },
            "text/json": {
              "schema": {
                "$ref": "#/components/schemas/DeleteCommentRequestDto"
              }
            },
            "application/*+json": {
              "schema": {
                "$ref": "#/components/schemas/DeleteCommentRequestDto"
              }
            }
          }
        },
        "responses": {
          "200": {
            "description": "OK"
          }
        }
      }
    },
    "/api/Like/GetLike": {
      "get": {
        "tags": [
          "Like"
        ],
        "responses": {
          "200": {
            "description": "OK"
          }
        }
      }
    },
    "/api/Like/GetById": {
      "get": {
        "tags": [
          "Like"
        ],
        "parameters": [
          {
            "name": "id",
            "in": "query",
            "schema": {
              "type": "integer",
              "format": "int32"
            }
          }
        ],
        "responses": {
          "200": {
            "description": "OK"
          }
        }
      }
    },
    "/api/Like/CreateLike": {
      "post": {
        "tags": [
          "Like"
        ],
        "requestBody": {
          "content": {
            "application/json": {
              "schema": {
                "$ref": "#/components/schemas/CreateLikeRequestDto"
              }
            },
            "text/json": {
              "schema": {
                "$ref": "#/components/schemas/CreateLikeRequestDto"
              }
            },
            "application/*+json": {
              "schema": {
                "$ref": "#/components/schemas/CreateLikeRequestDto"
              }
            }
          }
        },
        "responses": {
          "200": {
            "description": "OK"
          }
        }
      }
    },
    "/api/Like/DeleteLike": {
      "delete": {
        "tags": [
          "Like"
        ],
        "requestBody": {
          "content": {
            "application/json": {
              "schema": {
                "$ref": "#/components/schemas/DeleteLikeRequestDto"
              }
            },
            "text/json": {
              "schema": {
                "$ref": "#/components/schemas/DeleteLikeRequestDto"
              }
            },
            "application/*+json": {
              "schema": {
                "$ref": "#/components/schemas/DeleteLikeRequestDto"
              }
            }
          }
        },
        "responses": {
          "200": {
            "description": "OK"
          }
        }
      }
    },
    "/api/Post/GetPost": {
      "get": {
        "tags": [
          "Post"
        ],
        "responses": {
          "200": {
            "description": "OK"
          }
        }
      }
    },
    "/api/Post/GetById": {
      "get": {
        "tags": [
          "Post"
        ],
        "parameters": [
          {
            "name": "id",
            "in": "query",
            "schema": {
              "type": "integer",
              "format": "int32"
            }
          }
        ],
        "responses": {
          "200": {
            "description": "OK"
          }
        }
      }
    },
    "/api/Post/CreatePost": {
      "post": {
        "tags": [
          "Post"
        ],
        "requestBody": {
          "content": {
            "application/json": {
              "schema": {
                "$ref": "#/components/schemas/CreatePostRequestDto"
              }
            },
            "text/json": {
              "schema": {
                "$ref": "#/components/schemas/CreatePostRequestDto"
              }
            },
            "application/*+json": {
              "schema": {
                "$ref": "#/components/schemas/CreatePostRequestDto"
              }
            }
          }
        },
        "responses": {
          "200": {
            "description": "OK"
          }
        }
      }
    },
    "/api/Post/UpdatePost": {
      "post": {
        "tags": [
          "Post"
        ],
        "requestBody": {
          "content": {
            "application/json": {
              "schema": {
                "$ref": "#/components/schemas/UpdatePostRequestDto"
              }
            },
            "text/json": {
              "schema": {
                "$ref": "#/components/schemas/UpdatePostRequestDto"
              }
            },
            "application/*+json": {
              "schema": {
                "$ref": "#/components/schemas/UpdatePostRequestDto"
              }
            }
          }
        },
        "responses": {
          "200": {
            "description": "OK"
          }
        }
      }
    },
    "/api/Post/DeletePost": {
      "delete": {
        "tags": [
          "Post"
        ],
        "requestBody": {
          "content": {
            "application/json": {
              "schema": {
                "$ref": "#/components/schemas/DeletePostRequestDto"
              }
            },
            "text/json": {
              "schema": {
                "$ref": "#/components/schemas/DeletePostRequestDto"
              }
            },
            "application/*+json": {
              "schema": {
                "$ref": "#/components/schemas/DeletePostRequestDto"
              }
            }
          }
        },
        "responses": {
          "200": {
            "description": "OK"
          }
        }
      }
    },
    "/api/Role/GetAllRoles": {
      "get": {
        "tags": [
          "Role"
        ],
        "responses": {
          "200": {
            "description": "OK"
          }
        }
      }
    },
    "/api/Role/GetById": {
      "get": {
        "tags": [
          "Role"
        ],
        "parameters": [
          {
            "name": "id",
            "in": "query",
            "schema": {
              "type": "string"
            }
          }
        ],
        "responses": {
          "200": {
            "description": "OK"
          }
        }
      }
    },
    "/api/Role/CreateRole": {
      "post": {
        "tags": [
          "Role"
        ],
        "requestBody": {
          "content": {
            "application/json": {
              "schema": {
                "$ref": "#/components/schemas/CreateRoleRequestDto"
              }
            },
            "text/json": {
              "schema": {
                "$ref": "#/components/schemas/CreateRoleRequestDto"
              }
            },
            "application/*+json": {
              "schema": {
                "$ref": "#/components/schemas/CreateRoleRequestDto"
              }
            }
          }
        },
        "responses": {
          "200": {
            "description": "OK"
          }
        }
      }
    },
    "/api/Role/UpdateRole": {
      "put": {
        "tags": [
          "Role"
        ],
        "parameters": [
          {
            "name": "id",
            "in": "query",
            "schema": {
              "type": "string"
            }
          }
        ],
        "requestBody": {
          "content": {
            "application/json": {
              "schema": {
                "$ref": "#/components/schemas/UpdateRoleRequestDto"
              }
            },
            "text/json": {
              "schema": {
                "$ref": "#/components/schemas/UpdateRoleRequestDto"
              }
            },
            "application/*+json": {
              "schema": {
                "$ref": "#/components/schemas/UpdateRoleRequestDto"
              }
            }
          }
        },
        "responses": {
          "200": {
            "description": "OK"
          }
        }
      }
    },
    "/api/Role/DeleteRole": {
      "delete": {
        "tags": [
          "Role"
        ],
        "parameters": [
          {
            "name": "id",
            "in": "query",
            "schema": {
              "type": "string"
            }
          }
        ],
        "responses": {
          "200": {
            "description": "OK"
          }
        }
      }
    },
    "/api/User/GetAllUser": {
      "get": {
        "tags": [
          "User"
        ],
        "responses": {
          "200": {
            "description": "OK"
          }
        }
      }
    },
    "/api/User/GetById": {
      "get": {
        "tags": [
          "User"
        ],
        "parameters": [
          {
            "name": "id",
            "in": "query",
            "schema": {
              "type": "string"
            }
          }
        ],
        "responses": {
          "200": {
            "description": "OK"
          }
        }
      }
    },
    "/api/User/CreateUser": {
      "post": {
        "tags": [
          "User"
        ],
        "requestBody": {
          "content": {
            "application/json": {
              "schema": {
                "$ref": "#/components/schemas/CreateUserRequestDto"
              }
            },
            "text/json": {
              "schema": {
                "$ref": "#/components/schemas/CreateUserRequestDto"
              }
            },
            "application/*+json": {
              "schema": {
                "$ref": "#/components/schemas/CreateUserRequestDto"
              }
            }
          }
        },
        "responses": {
          "200": {
            "description": "OK"
          }
        }
      }
    },
    "/api/User/UpdateUser": {
      "put": {
        "tags": [
          "User"
        ],
        "parameters": [
          {
            "name": "id",
            "in": "query",
            "schema": {
              "type": "string"
            }
          }
        ],
        "requestBody": {
          "content": {
            "application/json": {
              "schema": {
                "$ref": "#/components/schemas/UpdateUserRequestDto"
              }
            },
            "text/json": {
              "schema": {
                "$ref": "#/components/schemas/UpdateUserRequestDto"
              }
            },
            "application/*+json": {
              "schema": {
                "$ref": "#/components/schemas/UpdateUserRequestDto"
              }
            }
          }
        },
        "responses": {
          "200": {
            "description": "OK"
          }
        }
      }
    },
    "/api/User/DeleteUser/{id}": {
      "delete": {
        "tags": [
          "User"
        ],
        "parameters": [
          {
            "name": "id",
            "in": "path",
            "required": true,
            "schema": {
              "type": "string"
            }
          }
        ],
        "responses": {
          "200": {
            "description": "OK"
          }
        }
      }
    }
  },
  "components": {
    "schemas": {
      "Category": {
        "type": "object",
        "properties": {
          "id": {
            "type": "integer",
            "format": "int32"
          },
          "createdAt": {
            "type": "string",
            "format": "date-time"
          },
          "updatedAt": {
            "type": "string",
            "format": "date-time"
          },
          "description": {
            "type": "string",
            "nullable": true
          },
          "name": {
            "type": "string",
            "nullable": true
          }
        },
        "additionalProperties": false
      },
      "CreateCategoryRequestDto": {
        "type": "object",
        "properties": {
          "name": {
            "type": "string",
            "nullable": true
          },
          "description": {
            "type": "string",
            "nullable": true
          }
        },
        "additionalProperties": false
      },
      "CreateCommentRequestDto": {
        "type": "object",
        "properties": {
          "content": {
            "type": "string",
            "nullable": true
          },
          "postId": {
            "type": "integer",
            "format": "int32"
          },
          "userId": {
            "type": "string",
            "nullable": true
          }
        },
        "additionalProperties": false
      },
      "CreateLikeRequestDto": {
        "type": "object",
        "properties": {
          "postId": {
            "type": "integer",
            "format": "int32"
          },
          "userId": {
            "type": "string",
            "nullable": true
          }
        },
        "additionalProperties": false
      },
      "CreatePostRequestDto": {
        "type": "object",
        "properties": {
          "content": {
            "type": "string",
            "nullable": true
          },
          "categoryId": {
            "type": "integer",
            "format": "int32"
          },
          "roleId": {
            "type": "string",
            "nullable": true
          },
          "userId": {
            "type": "string",
            "nullable": true
          }
        },
        "additionalProperties": false
      },
      "CreateRoleRequestDto": {
        "type": "object",
        "properties": {
          "name": {
            "type": "string",
            "nullable": true
          }
        },
        "additionalProperties": false
      },
      "CreateUserRequestDto": {
        "type": "object",
        "properties": {
          "firstName": {
            "type": "string",
            "nullable": true
          },
          "secondName": {
            "type": "string",
            "nullable": true
          },
          "email": {
            "type": "string",
            "nullable": true
          },
          "roleId": {
            "type": "string",
            "nullable": true
          }
        },
        "additionalProperties": false
      },
      "DeleteCategoryRequestDto": {
        "type": "object",
        "properties": {
          "id": {
            "type": "integer",
            "format": "int32"
          }
        },
        "additionalProperties": false
      },
      "DeleteCommentRequestDto": {
        "type": "object",
        "properties": {
          "id": {
            "type": "integer",
            "format": "int32"
          }
        },
        "additionalProperties": false
      },
      "DeleteLikeRequestDto": {
        "type": "object",
        "properties": {
          "id": {
            "type": "integer",
            "format": "int32"
          }
        },
        "additionalProperties": false
      },
      "DeletePostRequestDto": {
        "type": "object",
        "properties": {
          "id": {
            "type": "integer",
            "format": "int32"
          }
        },
        "additionalProperties": false
      },
      "Role": {
        "type": "object",
        "properties": {
          "id": {
            "type": "string",
            "nullable": true
          },
          "name": {
            "type": "string",
            "nullable": true
          },
          "normalizedName": {
            "type": "string",
            "nullable": true
          },
          "concurrencyStamp": {
            "type": "string",
            "nullable": true
          },
          "createdAt": {
            "type": "string",
            "format": "date-time"
          },
          "updatedAt": {
            "type": "string",
            "format": "date-time"
          }
        },
        "additionalProperties": false
      },
      "UpdateCategoryRequestDto": {
        "type": "object",
        "properties": {
          "id": {
            "type": "integer",
            "format": "int32"
          },
          "name": {
            "type": "string",
            "nullable": true
          },
          "description": {
            "type": "string",
            "nullable": true
          }
        },
        "additionalProperties": false
      },
      "UpdateCommentRequestDto": {
        "type": "object",
        "properties": {
          "id": {
            "type": "integer",
            "format": "int32"
          },
          "content": {
            "type": "string",
            "nullable": true
          }
        },
        "additionalProperties": false
      },
      "UpdatePostRequestDto": {
        "type": "object",
        "properties": {
          "id": {
            "type": "integer",
            "format": "int32"
          },
          "content": {
            "type": "string",
            "nullable": true
          },
          "category": {
            "$ref": "#/components/schemas/Category"
          },
          "categoryId": {
            "type": "integer",
            "format": "int32"
          },
          "user": {
            "$ref": "#/components/schemas/User"
          },
          "userId": {
            "type": "string",
            "nullable": true
          }
        },
        "additionalProperties": false
      },
      "UpdateRoleRequestDto": {
        "type": "object",
        "properties": {
          "id": {
            "type": "string",
            "nullable": true
          },
          "name": {
            "type": "string",
            "nullable": true
          },
          "createdAt": {
            "type": "string",
            "format": "date-time"
          },
          "updatedAt": {
            "type": "string",
            "format": "date-time"
          }
        },
        "additionalProperties": false
      },
      "UpdateUserRequestDto": {
        "type": "object",
        "properties": {
          "id": {
            "type": "string",
            "nullable": true
          },
          "firstName": {
            "type": "string",
            "nullable": true
          },
          "secondName": {
            "type": "string",
            "nullable": true
          },
          "email": {
            "type": "string",
            "nullable": true
          },
          "role": {
            "$ref": "#/components/schemas/Role"
          },
          "roleId": {
            "type": "string",
            "nullable": true
          },
          "createdAt": {
            "type": "string",
            "format": "date-time"
          },
          "updatedAt": {
            "type": "string",
            "format": "date-time"
          }
        },
        "additionalProperties": false
      },
      "User": {
        "type": "object",
        "properties": {
          "id": {
            "type": "string",
            "nullable": true
          },
          "userName": {
            "type": "string",
            "nullable": true
          },
          "normalizedUserName": {
            "type": "string",
            "nullable": true
          },
          "email": {
            "type": "string",
            "nullable": true
          },
          "normalizedEmail": {
            "type": "string",
            "nullable": true
          },
          "emailConfirmed": {
            "type": "boolean"
          },
          "passwordHash": {
            "type": "string",
            "nullable": true
          },
          "securityStamp": {
            "type": "string",
            "nullable": true
          },
          "concurrencyStamp": {
            "type": "string",
            "nullable": true
          },
          "phoneNumber": {
            "type": "string",
            "nullable": true
          },
          "phoneNumberConfirmed": {
            "type": "boolean"
          },
          "twoFactorEnabled": {
            "type": "boolean"
          },
          "lockoutEnd": {
            "type": "string",
            "format": "date-time",
            "nullable": true
          },
          "lockoutEnabled": {
            "type": "boolean"
          },
          "accessFailedCount": {
            "type": "integer",
            "format": "int32"
          },
          "firstName": {
            "type": "string",
            "nullable": true
          },
          "secondName": {
            "type": "string",
            "nullable": true
          },
          "createdAt": {
            "type": "string",
            "format": "date-time"
          },
          "updateAt": {
            "type": "string",
            "format": "date-time"
          },
          "role": {
            "$ref": "#/components/schemas/Role"
          },
          "roleId": {
            "type": "string",
            "nullable": true
          }
        },
        "additionalProperties": false
      }
    }
  }
}